gramax_sync/__init__.py
gramax_sync/exceptions.py
gramax_sync/auth/__init__.py
gramax_sync/auth/oauth.py
gramax_sync/auth/token_manager.py
gramax_sync/cli/__init__.py
gramax_sync/cli/auth.py
gramax_sync/cli/edit.py
gramax_sync/cli/init.py
gramax_sync/cli/main.py
gramax_sync/cli/update.py
gramax_sync/config/__init__.py
gramax_sync/config/config_manager.py
gramax_sync/config/local_config.py
gramax_sync/config/models.py
gramax_sync/config/parser.py
gramax_sync/core/__init__.py
gramax_sync/core/adapters.py
gramax_sync/core/protocols.py
gramax_sync/git/__init__.py
gramax_sync/git/operations.py
gramax_sync/git/status.py
gramax_sync/gitlab/__init__.py
gramax_sync/gitlab/client.py
gramax_sync/gitlab/exceptions.py
gramax_sync/mcp/__init__.py
gramax_sync/mcp/server.py
gramax_sync/mcp/tools.py
gramax_sync/utils/__init__.py
gramax_sync/utils/logging.py
gramax_sync/utils/output.py
gramax_sync/utils/selection.py
gramax_sync/workspace/__init__.py
gramax_sync/workspace/manager.py
gramax_sync-0.1.1.dist-info/METADATA
gramax_sync-0.1.1.dist-info/WHEEL
gramax_sync-0.1.1.dist-info/entry_points.txt
gramax_sync-0.1.1.dist-info/top_level.txt
gramax_sync-0.1.1.dist-info/RECORD
